JVaultRestServerClient_xethhung12/JVaultRestServerClient.py
jvaultrestserverclient_xethhung12-0.0.1.dist-info/METADATA
jvaultrestserverclient_xethhung12-0.0.1.dist-info/WHEEL
jvaultrestserverclient_xethhung12-0.0.1.dist-info/licenses/LICENSE
jvaultrestserverclient_xethhung12-0.0.1.dist-info/RECORD
