Metadata-Version: 2.4
Name: JVaultRestServerClient_xethhung12
Version: 0.0.1
Summary: A small example package
Project-URL: Homepage, https://github.com/pypa/sampleproject
Project-URL: Issues, https://github.com/pypa/sampleproject/issues
Author-email: Xeth Hung <admin@xethh.me>
License-Expression: MIT
License-File: LICENSE
Classifier: Operating System :: OS Independent
Classifier: Programming Language :: Python :: 3
Requires-Python: >=3.9
Requires-Dist: requests
